lunr_chatbot/__init__.py
lunr_chatbot/client.py
lunr_chatbot/encryption.py
lunr_chatbot/exceptions.py
lunr_chatbot/models.py
lunr_chatbot/websocket.py
lunr_chatbot-1.0.4.dist-info/METADATA
lunr_chatbot-1.0.4.dist-info/WHEEL
lunr_chatbot-1.0.4.dist-info/top_level.txt
lunr_chatbot-1.0.4.dist-info/RECORD
